pyguiadapter/__init__.py
pyguiadapter/action.py
pyguiadapter/adapter/__init__.py
pyguiadapter/adapter/adapter.py
pyguiadapter/adapter/ubeep.py
pyguiadapter/adapter/uclipboard.py
pyguiadapter/adapter/ucontext.py
pyguiadapter/adapter/udialog.py
pyguiadapter/adapter/uinput.py
pyguiadapter/adapter/uoutput.py
pyguiadapter/adapter/uprogress.py
pyguiadapter/adapter/useful.py
pyguiadapter/adapter/utoast.py
pyguiadapter/bundle.py
pyguiadapter/codeeditor/__init__.py
pyguiadapter/codeeditor/_example.py
pyguiadapter/codeeditor/actions.py
pyguiadapter/codeeditor/base.py
pyguiadapter/codeeditor/constants.py
pyguiadapter/codeeditor/editor.py
pyguiadapter/codeeditor/formatters/__init__.py
pyguiadapter/codeeditor/formatters/_json.py
pyguiadapter/codeeditor/formatters/_python.py
pyguiadapter/constants/__init__.py
pyguiadapter/constants/clipboard.py
pyguiadapter/constants/color.py
pyguiadapter/constants/font.py
pyguiadapter/exceptions.py
pyguiadapter/executor.py
pyguiadapter/executors/__init__.py
pyguiadapter/executors/thread.py
pyguiadapter/extend_types.py
pyguiadapter/fn.py
pyguiadapter/itemseditor/__init__.py
pyguiadapter/itemseditor/common_config.py
pyguiadapter/itemseditor/item_editor.py
pyguiadapter/itemseditor/itemsview.py
pyguiadapter/itemseditor/itemsview_container.py
pyguiadapter/itemseditor/listview/__init__.py
pyguiadapter/itemseditor/listview/_config.py
pyguiadapter/itemseditor/listview/_listview.py
pyguiadapter/itemseditor/multiobject_editor.py
pyguiadapter/itemseditor/object_editor.py
pyguiadapter/itemseditor/object_tableview/__init__.py
pyguiadapter/itemseditor/object_tableview/_commons.py
pyguiadapter/itemseditor/object_tableview/_delegate.py
pyguiadapter/itemseditor/object_tableview/_test_bool.py
pyguiadapter/itemseditor/object_tableview/_test_choice.py
pyguiadapter/itemseditor/object_tableview/_test_color.py
pyguiadapter/itemseditor/object_tableview/_test_date.py
pyguiadapter/itemseditor/object_tableview/_test_datetime.py
pyguiadapter-1.0.10.dist-info/LICENSE
pyguiadapter-1.0.10.dist-info/METADATA
pyguiadapter-1.0.10.dist-info/WHEEL
pyguiadapter-1.0.10.dist-info/RECORD
