Metadata-Version: 2.1
Name: pyguiadapter
Version: 1.0.10
Summary: A gui library which can turn almost any python function into a gui application
Author: zimolab
Author-email: zimolab@aliyun.com
Requires-Python: >=3.8,<3.14
Classifier: Programming Language :: Python :: 3
Classifier: Programming Language :: Python :: 3.8
Classifier: Programming Language :: Python :: 3.9
Classifier: Programming Language :: Python :: 3.10
Classifier: Programming Language :: Python :: 3.11
Classifier: Programming Language :: Python :: 3.12
Requires-Dist: docstring-parser (>=0.16,<0.17)
Requires-Dist: pyqcodeeditor (>=0.3.7)
Requires-Dist: qtawesome (>=1.3.1,<2.0.0)
Requires-Dist: qtpy (>=2.4.1,<3.0.0)
Requires-Dist: tomlkit (>=0.13.2,<0.14.0)
Requires-Dist: yapf (>=0.40.2,<0.41.0)
